Metadata-Version: 2.1
Name: webvtt-translator
Version: 0.1.0
Summary: An automated translator of WebVTT (Web Video Text Tracks) from one language to another using generative AI.
Home-page: https://github.com/yourusername/my-python-project
Author: Sergio Sousa
Author-email: shenrique@gmail.com
Classifier: Programming Language :: Python :: 3
Classifier: License :: OSI Approved :: MIT License
Classifier: Operating System :: OS Independent
Requires-Python: >=3.6
